jupyter_micropython_kernel/__init__.py
jupyter_micropython_kernel/__main__.py
jupyter_micropython_kernel/deviceconnector.py
jupyter_micropython_kernel/install.py
jupyter_micropython_kernel/kernel.py
jupyter_micropython_kernel-0.1.3.2.dist-info/LICENSE
jupyter_micropython_kernel-0.1.3.2.dist-info/WHEEL
jupyter_micropython_kernel-0.1.3.2.dist-info/METADATA
jupyter_micropython_kernel-0.1.3.2.dist-info/RECORD
