Metadata-Version: 2.1
Name: jupyter_micropython_kernel
Version: 0.1.3.2
Summary: Jupyter kernel to interact with a MicroPython ESP8266 or ESP32 over its serial REPL.
Home-page: https://github.com/goatchurchprime/jupyter_micropython_kernel
License: UNKNOWN
Author: Julian Todd, Tony DiCola
Author-email: julian@goatchurch.org.uk
Requires-Python: >=3.0
Classifier: Intended Audience :: Developers
Classifier: License :: OSI Approved :: BSD License
Classifier: Operating System :: OS Independent
Classifier: Programming Language :: Python
Classifier: Programming Language :: Python :: 3
Classifier: Programming Language :: Python :: 3.6
Classifier: Programming Language :: Python :: 3.7
Classifier: Programming Language :: Python :: 3.8
Classifier: Programming Language :: Python :: 3 :: Only
Classifier: Topic :: Software Development :: Libraries :: Python Modules
Requires-Dist: pyserial>=3.4
Requires-Dist: websocket-client>=0.44
